pypickup/__init__.py
pypickup/__main__.py
pypickup/cli.py
pypickup/controller.py
pypickup/cmd/__init__.py
pypickup/cmd/add.py
pypickup/cmd/config.py
pypickup/cmd/list.py
pypickup/cmd/rebuildIndexEP.py
pypickup/cmd/remove.py
pypickup/settings/wheelFilters.py
pypickup/utils/htmlManager.py
pypickup/utils/networkManager.py
pypickup-0.3.6.dist-info/LICENSE
pypickup-0.3.6.dist-info/METADATA
pypickup-0.3.6.dist-info/WHEEL
pypickup-0.3.6.dist-info/entry_points.txt
pypickup-0.3.6.dist-info/top_level.txt
pypickup-0.3.6.dist-info/RECORD
