Metadata-Version: 2.1
Name: pypickup
Version: 0.3.6
Summary: An utility to generate a local PyPI cache for selected packages based on the PyPI.org repositories.
Author-email: German Navarro <ge.najim@gmail.com>, Sergio Sánchez Ramírez <sergio.sanchez.ramirez@bsc.es>
License: Apache License
Project-URL: Homepage, https://github.com/UB-Quantic/pypickup
Classifier: Programming Language :: Python :: 3
Classifier: License :: OSI Approved :: Apache Software License
Classifier: Operating System :: OS Independent
Classifier: Topic :: System :: Archiving :: Mirroring
Requires-Python: >=3.8
License-File: LICENSE
Requires-Dist: beautifulsoup4 ==4.11.1
Requires-Dist: wheel-filename ==1.4.1
Requires-Dist: multimethod ==1.9
Requires-Dist: requests ==2.31.0
Requires-Dist: tqdm ==4.64.1
Requires-Dist: PyYAML ==6.0
Requires-Dist: pytest-cov ==4.0.0
